{
	"fullUrl": "urn:uuid:a54219b8-f741-4c47-b662-e4f8dfa49ab6",
	"resource": {
		"resourceType": "MedicationRequest",
		"extension": [
			{
				"url": "https://fhir.nhs.uk/StructureDefinition/Extension-EPS-DispensingInformation",
				"extension": [
					{
						"url": "dispenseStatus",
						"valueCoding": {
							"system": "https://fhir.nhs.uk/CodeSystem/medicationdispense-type",
							"code": "0008",
							"display": "Item with dispenser"
						}
					}
				]
			},
			{
				"url": "https://fhir.nhs.uk/StructureDefinition/Extension-DM-PrescriptionType",
				"valueCoding": {
					"system": "https://fhir.nhs.uk/CodeSystem/prescription-type",
					"code": "0101",
					"display": "Primary Care Prescriber - Medical Prescriber"
				}
			}
		],
		"identifier": [
			{
				"system": "https://fhir.nhs.uk/Id/prescription-order-item-number",
				"value": "a54219b8-f741-4c47-b662-e4f8dfa49ab6"
			}
		],
		"status": "active",
		"intent": "order",
		"category": [
			{
				"coding": [
					{
						"system": "http://terminology.hl7.org/CodeSystem/medicationrequest-category",
						"code": "community",
						"display": "Community"
					}
				]
			}
		],
		"medicationCodeableConcept": {
			"coding": [
				{
					"system": "http://snomed.info/sct",
					"code": "39732311000001104",
					"display": "Amoxicillin 250mg capsules"
				}
			]
		},
		"subject": {
			"reference": "urn:uuid:78d3c2eb-009e-4ec8-a358-b042954aa9b2"
		},
		"authoredOn": "2022-10-21T13:47:00+00:00",
		"requester": {
			"reference": "urn:uuid:56166769-c1c4-4d07-afa8-132b5dfca666"
		},
		"groupIdentifier": {
			"system": "https://fhir.nhs.uk/Id/prescription-order-number",
			"value": "24F5DA-A83008-7EFE6Z",
			"extension": [
				{
					"url": "https://fhir.nhs.uk/StructureDefinition/Extension-DM-PrescriptionId",
					"valueIdentifier": {
						"system": "https://fhir.nhs.uk/Id/prescription",
						"value": "20ba5fb5-cb58-462c-923e-22d180b09356"
					}
				}
			]
		},
		"courseOfTherapyType": {
			"coding": [
				{
					"system": "http://terminology.hl7.org/CodeSystem/medicationrequest-course-of-therapy",
					"code": "acute",
					"display": "Short course (acute) therapy"
				}
			]
		},
		"dosageInstruction": [
			{
				"text": "2 times a day for 10 days",
				"timing": {
					"repeat": {
						"frequency": 2,
						"period": 1,
						"periodUnit": "d"
					}
				},
				"route": {
					"coding": [
						{
							"system": "http://snomed.info/sct",
							"code": "26643006",
							"display": "Oral"
						}
					]
				}
			}
		],
		"dispenseRequest": {
			"extension": [
				{
					"url": "https://fhir.nhs.uk/StructureDefinition/Extension-DM-PerformerSiteType",
					"valueCoding": {
						"system": "https://fhir.nhs.uk/CodeSystem/dispensing-site-preference",
						"code": "P1"
					}
				}
			],
			"validityPeriod": {
				"start": "2022-10-21"
			},
			"quantity": {
				"value": 20,
				"unit": "tablet",
				"system": "http://snomed.info/sct",
				"code": "428673006"
			},
			"expectedSupplyDuration": {
				"value": 10,
				"unit": "day",
				"system": "http://unitsofmeasure.org",
				"code": "d"
			},
			"performer": {
				"identifier": {
					"system": "https://fhir.nhs.uk/Id/ods-organization-code",
					"value": "VNE51"
				}
			}
		},
		"substitution": {
			"allowedBoolean": false
		}
	}
}
